combine_notebooks/__init__.py
combine_notebooks/cellml_utilities.py
combine_notebooks/combine_files.py
combine_notebooks/convert_notebooks.py
combine_notebooks/py.typed
combine_notebooks/examples/__init__.py
combine_notebooks/examples/example_biopax.py
combine_notebooks/examples/example_cellml.py
combine_notebooks/examples/example_neuroml.py
combine_notebooks/examples/example_omex.py
combine_notebooks/examples/example_sbgn.py
combine_notebooks/examples/example_sbml_antimony.py
combine_notebooks/examples/example_sbml_libsbml.py
combine_notebooks/examples/example_sbml_sbmlutils.py
combine_notebooks/examples/example_sbol.py
combine_notebooks/examples/example_sedml.py
combine_notebooks/validation/__init__.py
combine_notebooks/validation/validation_sbgn.py
combine_notebooks/validation/validation_sbml.py
combine_notebooks/validation/validation_sedml.py
combine_notebooks-0.1.4.dist-info/LICENSE
combine_notebooks-0.1.4.dist-info/METADATA
combine_notebooks-0.1.4.dist-info/WHEEL
combine_notebooks-0.1.4.dist-info/top_level.txt
combine_notebooks-0.1.4.dist-info/zip-safe
combine_notebooks-0.1.4.dist-info/RECORD
