Metadata-Version: 2.1
Name: combine-notebooks
Version: 0.1.4
Summary: combine_notebooks - COMBINE jupyter notebooks in python.
Home-page: https://github.com/combine-org/combine-notebooks
Download-URL: https://pypi.org/project/combine_notebooks
Author: Matthias Koenig & Aditya Singhal
Author-email: konigmatt@googlemail.com
Maintainer: Matthias Koenig
Maintainer-email: konigmatt@googlemail.com
License: LGPL-3.0
Project-URL: Source Code, https://github.com/combine-org/combine-notebooks
Project-URL: Documentation, https://github.com/combine-org/combine-notebooks
Project-URL: Bug Tracker, https://github.com/combine-org/combine-notebooks/issues
Keywords: modeling,standardization,COMBINE,metadata,archive,annotation
Classifier: Development Status :: 4 - Beta
Classifier: Intended Audience :: Science/Research
Classifier: License :: OSI Approved :: GNU Lesser General Public License v3 (LGPLv3)
Classifier: Operating System :: OS Independent
Classifier: Programming Language :: Python :: 3.8
Classifier: Programming Language :: Python :: 3.9
Classifier: Programming Language :: Python :: 3.10
Classifier: Programming Language :: Python :: Implementation :: CPython
Classifier: Topic :: Scientific/Engineering
Classifier: Topic :: Scientific/Engineering :: Bio-Informatics
Requires-Python: >=3.8
License-File: LICENSE
Requires-Dist: depinfo (>=2.0.0)
Requires-Dist: python-libsbml (>=5.19.5)
Requires-Dist: python-libsedml (>=2.0.32)
Requires-Dist: sbmlutils (>=0.7.6)
Requires-Dist: antimony (>=2.13.1)
Requires-Dist: pyneuroml (>=0.7.1)
Requires-Dist: libcellml (>=0.3.104)
Requires-Dist: libsbgnpy (>=0.2.2)
Requires-Dist: pybiopax (>=0.1.2)
Requires-Dist: ipython (>=8.4.0)
Requires-Dist: nbformat (>=5.4.0)
Provides-Extra: development
Requires-Dist: pip-tools (>6.5.1) ; extra == 'development'
Requires-Dist: black (>=22.1.0) ; extra == 'development'
Requires-Dist: bump2version (>=1.0.1) ; extra == 'development'
Requires-Dist: isort (>=5.10.1) ; extra == 'development'
Requires-Dist: tox (>=3.24.3) ; extra == 'development'
Requires-Dist: flake8 (>=4.0.1) ; extra == 'development'
Requires-Dist: flake8-mypy (>=17.8.0) ; extra == 'development'
Requires-Dist: mypy (>=0.931) ; extra == 'development'
Requires-Dist: pytest (>=7.0.1) ; extra == 'development'
Requires-Dist: pytest-cov (>=3.0.0) ; extra == 'development'
